lektor_rstfile.py
lektor_rstfile-0.2.dist-info/DESCRIPTION.rst
lektor_rstfile-0.2.dist-info/METADATA
lektor_rstfile-0.2.dist-info/RECORD
lektor_rstfile-0.2.dist-info/WHEEL
lektor_rstfile-0.2.dist-info/entry_points.txt
lektor_rstfile-0.2.dist-info/metadata.json
lektor_rstfile-0.2.dist-info/top_level.txt
